pwsearch/__init__.py
pwsearch/__main__.py
pwsearch/pwsearch.py
pwsearch-1.4.3.dist-info/LICENSE
pwsearch-1.4.3.dist-info/METADATA
pwsearch-1.4.3.dist-info/WHEEL
pwsearch-1.4.3.dist-info/entry_points.txt
pwsearch-1.4.3.dist-info/top_level.txt
pwsearch-1.4.3.dist-info/RECORD
